MANIFEST.in
README.rst
new-theme.py
setup.py
Quokka_Themes.egg-info/PKG-INFO
Quokka_Themes.egg-info/SOURCES.txt
Quokka_Themes.egg-info/dependency_links.txt
Quokka_Themes.egg-info/not-zip-safe
Quokka_Themes.egg-info/pbr.json
Quokka_Themes.egg-info/requires.txt
Quokka_Themes.egg-info/top_level.txt
base_theme/info.json
base_theme/license.txt
base_theme/static/style.css
base_theme/templates/layout.html
quokka_themes/__init__.py
tests/test-themes.py
tests/morethemes/cool/info.json
tests/morethemes/cool/templates/active.html
tests/morethemes/cool/templates/hello.html
tests/morethemes/cool/templates/static.html
tests/templates/active.html
tests/templates/hello.html
tests/templates/static.html
tests/templates/static_parent.html
tests/themes/cool/info.json
tests/themes/cool/templates/hello.html
tests/themes/identifier/info.json
tests/themes/notthis/info.json
tests/themes/plain/info.json
tests/themes/plain/license.txt
tests/themes/plain/templates/static.html
tests/themes/warm-theme/info.json