Metadata-Version: 1.1
Name: Quokka-Themes
Version: 0.1.4
Summary: Provides infrastructure for theming Quokka applications
Home-page: https://github.com/pythonhub/quokka-themes
Author: Bruno Rocha
Author-email: rochacbruno@gmail.com
License: MIT
Keywords: flask themes theming style
Platform: any
Classifier: Development Status :: 4 - Beta
Classifier: Environment :: Web Environment
Classifier: Intended Audience :: Developers
Classifier: License :: OSI Approved :: MIT License
Classifier: Operating System :: OS Independent
Classifier: Programming Language :: Python
Classifier: Topic :: Internet :: WWW/HTTP :: Dynamic Content
Classifier: Topic :: Software Development :: Libraries :: Python Modules
